strindex/__init__.py
strindex/__main__.py
strindex/gui.py
strindex/strindex.py
strindex/utils.py
strindex/filetypes/__init__.py
strindex/filetypes/force.py
strindex/filetypes/iff.py
strindex/filetypes/pe.py
strindex-3.8.0.dist-info/LICENSE
strindex-3.8.0.dist-info/METADATA
strindex-3.8.0.dist-info/WHEEL
strindex-3.8.0.dist-info/entry_points.txt
strindex-3.8.0.dist-info/top_level.txt
strindex-3.8.0.dist-info/RECORD
