Metadata-Version: 2.1
Name: strindex
Version: 3.8.0
Summary: A command line utility to extract and patch strings of some filetypes, with a focus on compatibility and translation.
Home-page: https://github.com/zWolfrost/strindex
Author: zWolfrost
Author-email: zwolfrost@gmail.com
License: MIT
Keywords: PE strings patching translation
Platform: UNKNOWN
Classifier: Development Status :: 5 - Production/Stable
Classifier: Topic :: Utilities
Classifier: License :: OSI Approved :: MIT License
License-File: LICENSE
Requires-Dist: pefile (>=2024.8.26)
Provides-Extra: filter_language
Requires-Dist: lingua-language-detector ; extra == 'filter_language'
Provides-Extra: gui
Requires-Dist: pyside6 ; extra == 'gui'
Provides-Extra: spellcheck
Requires-Dist: language-tool-python ; extra == 'spellcheck'
